[
  {
    "id": "testosterone-total-test",
    "provider": "Quest Diagnostics",
    "name": "Testosterone Total Test",
    "price": 52.95,
    "drawFee": null,
    "markers": [
      "TESTOSTERONE, TOTAL,"
    ],
    "url": "https://www.ultalabtests.com/test/testosterone-total-test"
  },
  {
    "id": "testosterone-replacement-therapy-trt-panel",
    "provider": "Quest Diagnostics",
    "name": "Testosterone Replacement Therapy (TRT) Panel",
    "price": 90.95,
    "drawFee": null,
    "markers": [
      "Absolute Band Neutrophils (Only Reported If Detected)",
      "Absolute Basophils",
      "Absolute Blasts (Only Reported If Detected)",
      "Absolute Eosinophils",
      "Absolute Lymphocytes",
      "Absolute Metamyelocytes (Only Reported If Detected)",
      "Absolute Monocytes",
      "Absolute Myelocytes (Only Reported If Detected)",
      "Absolute Neutrophils",
      "Absolute Nucleated Rbc (Only Reported If Detected)",
      "Absolute Promyelocytes (Only Reported If Detected)",
      "Band Neutrophils (Only Reported If Detected)",
      "Basophils",
      "Blasts (Only Reported If Detected)",
      "Eosinophils",
      "Hematocrit",
      "Hemoglobin",
      "Lymphocytes",
      "MCH",
      "MCHC",
      "MCV",
      "Metamyelocytes (Only Reported If Detected)",
      "Monocytes",
      "MPV",
      "Myelocytes (Only Reported If Detected)",
      "Neutrophils",
      "Nucleated Rbc (Only Reported If Detected)",
      "Platelet Count",
      "Promyelocytes (Only Reported If Detected)",
      "RDW",
      "Reactive Lymphocytes (Only Reported If Detected)",
      "Red Blood Cell Count",
      "White Blood Cell Count",
      "Psa, Total",
      "Free Testosterone",
      "TESTOSTERONE, TOTAL,"
    ],
    "url": "https://www.ultalabtests.com/test/testosterone-replacement-therapy-trt-panel"
  }
]